MANIFEST.in
README.md
setup.cfg
setup.py
collective/__init__.py
collective.css3buttons.egg-info/PKG-INFO
collective.css3buttons.egg-info/SOURCES.txt
collective.css3buttons.egg-info/dependency_links.txt
collective.css3buttons.egg-info/entry_points.txt
collective.css3buttons.egg-info/namespace_packages.txt
collective.css3buttons.egg-info/not-zip-safe
collective.css3buttons.egg-info/requires.txt
collective.css3buttons.egg-info/top_level.txt
collective/css3buttons/__init__.py
collective/css3buttons/configure.zcml
collective/css3buttons/css3buttons/LICENSE.txt
collective/css3buttons/css3buttons/README.md
collective/css3buttons/css3buttons/demo.html
collective/css3buttons/css3buttons/images/css3buttons_backgrounds.png
collective/css3buttons/css3buttons/images/css3buttons_icons.png
collective/css3buttons/css3buttons/stylesheets/css3buttons.css
collective/css3buttons/css3buttons/stylesheets/demo.css
collective/css3buttons/css3buttons/stylesheets/reset.css
collective/css3buttons/profiles/default/cssregistry.xml
collective/css3buttons/profiles/default/metadata.xml
collective/css3buttons/tests/__init__.py
collective/css3buttons/tests/base.py
collective/css3buttons/tests/test_resource.py
docs/HISTORY.txt
docs/LICENSE.txt