Metadata-Version: 1.0
Name: collective.css3buttons
Version: 0.1
Summary: Simple framework for creating button links
Home-page: UNKNOWN
Author: Tommy Yu
Author-email: y@metatoaster.com
License: Unlicense
Platform: UNKNOWN
Classifier: Programming Language :: Python
Classifier: Topic :: Software Development :: Libraries :: Python Modules
